{"is_source_file": true, "format": "JavaScript (React JSX)", "description": "This file defines the main React component 'App' for a simple notes application. It manages the app's state, theme toggling, note addition/deletion, and rendering of UI elements. It also includes utility functions for formatting time and generating unique IDs.", "external_files": ["./App.css"], "external_methods": ["localStorage.getItem", "localStorage.setItem", "document.documentElement.setAttribute", "crypto.randomUUID"], "published": ["App", "formatTime", "cryptoRandomId"], "classes": [], "methods": [{"name": "App()", "description": "Main React functional component for the notes application.", "scope": "", "scopeKind": ""}, {"name": "formatTime(ts)", "description": "Formats a timestamp into a human-readable string.", "scope": "", "scopeKind": ""}, {"name": "cryptoRandomId()", "description": "Generates a unique ID for notes, using crypto API if available or fallback.", "scope": "", "scopeKind": ""}], "calls": ["localStorage.getItem", "localStorage.setItem", "document.documentElement.setAttribute", "React.useState", "React.useEffect", "JSON.parse", "JSON.stringify", "setNotes", "setTheme", "Date.now", "new Date", "localeString"], "search-terms": ["React App component", "localStorage notes persistence", "theme toggle button", "add note form", "delete note", "note ID generation", "notes array", "notes rendering", "time formatting"], "state": 2, "file_id": 8, "knowledge_revision": 25, "git_revision": "9e64feb9f8949a50eeb682443dc56a5e3eaf8b08", "ctags": [{"_type": "tag", "name": "1000", "path": "/home/kavia/workspace/code-generation/note-keeper-18406-18415/notes_frontend/src/App.js", "pattern": "/^              maxLength={1000}$/", "language": "JavaScript", "kind": "field", "scope": "App.maxLength", "scopeKind": "class"}, {"_type": "tag", "name": "App", "path": "/home/kavia/workspace/code-generation/note-keeper-18406-18415/notes_frontend/src/App.js", "pattern": "/^function App() {$/", "language": "JavaScript", "kind": "function", "signature": "()"}, {"_type": "tag", "name": "Switch to ${theme === 'light' ? 'dark' : 'light'} mode", "path": "/home/kavia/workspace/code-generation/note-keeper-18406-18415/notes_frontend/src/App.js", "pattern": "/^            aria-label={`Switch to ${theme === 'light' ? 'dark' : 'light'} mode`}$/", "language": "JavaScript", "kind": "field", "scope": "App.aria", "scopeKind": "class"}, {"_type": "tag", "name": "cryptoRandomId", "path": "/home/kavia/workspace/code-generation/note-keeper-18406-18415/notes_frontend/src/App.js", "pattern": "/^function cryptoRandomId() {$/", "language": "JavaScript", "kind": "function", "signature": "()"}, {"_type": "tag", "name": "formatTime", "path": "/home/kavia/workspace/code-generation/note-keeper-18406-18415/notes_frontend/src/App.js", "pattern": "/^function formatTime(ts) {$/", "language": "JavaScript", "kind": "function", "signature": "(ts)"}, {"_type": "tag", "name": "id", "path": "/home/kavia/workspace/code-generation/note-keeper-18406-18415/notes_frontend/src/App.js", "pattern": "/^      id: cryptoRandomId(),$/", "language": "JavaScript", "kind": "property", "scope": "App.newNote", "scopeKind": "class"}, {"_type": "tag", "name": "isAddDisabled", "path": "/home/kavia/workspace/code-generation/note-keeper-18406-18415/notes_frontend/src/App.js", "pattern": "/^              aria-disabled={isAddDisabled}$/", "language": "JavaScript", "kind": "field", "scope": "App.aria", "scopeKind": "class"}, {"_type": "tag", "name": "isAddDisabled", "path": "/home/kavia/workspace/code-generation/note-keeper-18406-18415/notes_frontend/src/App.js", "pattern": "/^              disabled={isAddDisabled}$/", "language": "JavaScript", "kind": "field", "scope": "App.disabled", "scopeKind": "class"}, {"_type": "tag", "name": "isAddDisabled", "path": "/home/kavia/workspace/code-generation/note-keeper-18406-18415/notes_frontend/src/App.js", "pattern": "/^              title={isAddDisabled ? 'Enter some text to add a note' : 'Add note'}$/", "language": "JavaScript", "kind": "field", "scope": "App.title", "scopeKind": "class"}, {"_type": "tag", "name": "newNote", "path": "/home/kavia/workspace/code-generation/note-keeper-18406-18415/notes_frontend/src/App.js", "pattern": "/^    const newNote = {$/", "language": "JavaScript", "kind": "class", "scope": "App", "scopeKind": "class"}, {"_type": "tag", "name": "noteText", "path": "/home/kavia/workspace/code-generation/note-keeper-18406-18415/notes_frontend/src/App.js", "pattern": "/^              value={noteText}$/", "language": "JavaScript", "kind": "field", "scope": "App.value", "scopeKind": "class"}, {"_type": "tag", "name": "text", "path": "/home/kavia/workspace/code-generation/note-keeper-18406-18415/notes_frontend/src/App.js", "pattern": "/^      text,$/", "language": "JavaScript", "kind": "field", "scope": "App.newNote", "scopeKind": "class"}, {"_type": "tag", "name": "toggleTheme", "path": "/home/kavia/workspace/code-generation/note-keeper-18406-18415/notes_frontend/src/App.js", "pattern": "/^            onClick={toggleTheme}$/", "language": "JavaScript", "kind": "field", "scope": "App.onClick", "scopeKind": "class"}], "hash": "5433249851003137a247a2d0fbeccc3e", "format-version": 4, "code-base-name": "notes_frontend", "filename": "notes_frontend/src/App.js", "fields": [{"name": "maxLength={1000}", "scope": "App.maxLength", "scopeKind": "class", "description": "unavailable"}, {"name": "aria-label={`Switch to ${theme === 'light' ? 'dark' : 'light'} mode`}", "scope": "App.aria", "scopeKind": "class", "description": "unavailable"}, {"name": "id: cryptoRandomId(),", "scope": "App.newNote", "scopeKind": "class", "description": "unavailable"}, {"name": "aria-disabled={isAddDisabled}", "scope": "App.aria", "scopeKind": "class", "description": "unavailable"}, {"name": "disabled={isAddDisabled}", "scope": "App.disabled", "scopeKind": "class", "description": "unavailable"}, {"name": "title={isAddDisabled ? 'Enter some text to add a note' : 'Add note'}", "scope": "App.title", "scopeKind": "class", "description": "unavailable"}, {"name": "value={noteText}", "scope": "App.value", "scopeKind": "class", "description": "unavailable"}, {"name": "text,", "scope": "App.newNote", "scopeKind": "class", "description": "unavailable"}, {"name": "onClick={toggleTheme}", "scope": "App.onClick", "scopeKind": "class", "description": "unavailable"}], "revision_history": [{"25": "9e64feb9f8949a50eeb682443dc56a5e3eaf8b08"}]}